tei_excel_tools/__init__.py
tei_excel_tools/_modidx.py
tei_excel_tools/core.py
tei_excel_tools-0.0.2.dist-info/LICENSE
tei_excel_tools-0.0.2.dist-info/METADATA
tei_excel_tools-0.0.2.dist-info/WHEEL
tei_excel_tools-0.0.2.dist-info/entry_points.txt
tei_excel_tools-0.0.2.dist-info/top_level.txt
tei_excel_tools-0.0.2.dist-info/RECORD
